hermes/__version__.py
hermes/cli.py
hermes/base/__init__.py
hermes/base/delay_estimator.py
hermes/base/state_interface.py
hermes/base/stream.py
hermes/base/broker/__init__.py
hermes/base/broker/broker.py
hermes/base/broker/broker_interface.py
hermes/base/broker/broker_states.py
hermes/base/nodes/__init__.py
hermes/base/nodes/consumer.py
hermes/base/nodes/consumer_interface.py
hermes/base/nodes/node.py
hermes/base/nodes/node_interface.py
hermes/base/nodes/node_states.py
hermes/base/nodes/pipeline.py
hermes/base/nodes/pipeline_interface.py
hermes/base/nodes/producer.py
hermes/base/nodes/producer_interface.py
hermes/base/storage/__init__.py
hermes/base/storage/storage.py
hermes/base/storage/storage_interface.py
hermes/base/storage/storage_states.py
hermes/datastructures/__init__.py
hermes/datastructures/cache.py
hermes/datastructures/fifo.py
hermes/dummy/__init__.py
hermes/dummy/consumer.py
hermes/dummy/pipeline.py
hermes/dummy/producer.py
hermes/dummy/stream.py
hermes/logger/__init__.py
hermes/logger/consumer.py
hermes/utils/__init__.py
hermes/utils/angle_utils.py
hermes/utils/argparse_utils.py
hermes/utils/di_utils.py
hermes/utils/dict_utils.py
hermes/utils/mp_utils.py
hermes/utils/msgpack_utils.py
hermes/utils/node_utils.py
hermes/utils/numpy_utils.py
hermes/utils/print_utils.py
hermes/utils/sensor_utils.py
hermes/utils/time_utils.py
hermes/utils/types.py
hermes/utils/zmq_utils.py
pysio_hermes-0.2.0.dist-info/licenses/LICENSE
pysio_hermes-0.2.0.dist-info/licenses/LOGO_LICENSE.md
pysio_hermes-0.2.0.dist-info/METADATA
pysio_hermes-0.2.0.dist-info/WHEEL
pysio_hermes-0.2.0.dist-info/entry_points.txt
pysio_hermes-0.2.0.dist-info/top_level.txt
pysio_hermes-0.2.0.dist-info/RECORD
