Metadata-Version: 2.4
Name: pysio-hermes
Version: 0.2.0
Summary: A realtime physiological sensing and edge AI processing framework
Author-email: Maxim Yudayev <maxim.yudayev@gmail.com>, "e-Media Research Lab @ KU Leuven" <emedia@kuleuven.be>
License-Expression: MIT
Project-URL: Homepage, https://yudayev.com/hermes
Project-URL: Documentation, https://yudayev.com/hermes
Project-URL: Repository, https://github.com/maximyudayev/hermes.git
Project-URL: Issues, https://github.com/maximyudayev/hermes/issues
Project-URL: Changelog, https://github.com/maximyudayev/hermes/blob/main/CHANGELOG.md
Keywords: embedded ai,wearables,sensors,streaming,realtime processing,physiology
Classifier: Programming Language :: Python :: 3
Classifier: Operating System :: OS Independent
Classifier: Development Status :: 4 - Beta
Classifier: Intended Audience :: Healthcare Industry
Classifier: Intended Audience :: Education
Classifier: Intended Audience :: Developers
Classifier: Intended Audience :: Science/Research
Classifier: Topic :: Scientific/Engineering
Classifier: Topic :: Scientific/Engineering :: Artificial Intelligence
Classifier: Topic :: Scientific/Engineering :: Medical Science Apps.
Classifier: Topic :: System :: Distributed Computing
Requires-Python: >=3.7
License-File: LICENSE
License-File: LOGO_LICENSE.md
Requires-Dist: pyzmq
Requires-Dist: msgpack
Requires-Dist: ffmpeg-python
Requires-Dist: h5py
Requires-Dist: numpy
Requires-Dist: pandas
Requires-Dist: pyyaml
Requires-Dist: pyusb
Requires-Dist: pyserial
Requires-Dist: pyperclip
Requires-Dist: openpyxl
Requires-Dist: orjson
Dynamic: license-file
